mt5_grpc_server/__init__.py
mt5_grpc_server/grpc_server.py
mt5_grpc_server/logging_interceptor.py
mt5_grpc_server/imp/__init__.py
mt5_grpc_server/imp/account_service.py
mt5_grpc_server/imp/deals_history.py
mt5_grpc_server/imp/history_orders.py
mt5_grpc_server/imp/initialize.py
mt5_grpc_server/imp/market_book.py
mt5_grpc_server/imp/market_data.py
mt5_grpc_server/imp/metatrader.py
mt5_grpc_server/imp/order.py
mt5_grpc_server/imp/order_calc.py
mt5_grpc_server/imp/order_check.py
mt5_grpc_server/imp/positions.py
mt5_grpc_server/imp/symbol_info.py
mt5_grpc_server/imp/symbol_info_tick.py
mt5_grpc_server/imp/symbols.py
mt5_grpc_server/imp/terminal_info.py
mt5_grpc_server/imp/trade.py
mt5_grpc_server-0.2.1.dist-info/METADATA
mt5_grpc_server-0.2.1.dist-info/WHEEL
mt5_grpc_server-0.2.1.dist-info/entry_points.txt
mt5_grpc_server-0.2.1.dist-info/top_level.txt
mt5_grpc_server-0.2.1.dist-info/RECORD
