Metadata-Version: 2.4
Name: mt5_grpc_server
Version: 0.2.1
Summary: MetaTrader 5 gRPC Server for remote trading operations
Home-page: https://github.com/Starmel/Metatrader5-gRPC-server
Author: starmel
Author-email: slava.kornienko16@gmail.com
Project-URL: Documentation, https://github.com/Starmel/Metatrader5-gRPC-server/tree/main/docs
Project-URL: Source, https://github.com/Starmel/Metatrader5-gRPC-server
Project-URL: Tracker, https://github.com/Starmel/Metatrader5-gRPC-server/issues
Keywords: metatrader,mt5,trading,grpc,server,api
Classifier: Development Status :: 4 - Beta
Classifier: Intended Audience :: Developers
Classifier: Intended Audience :: Financial and Insurance Industry
Classifier: Programming Language :: Python :: 3.8
Classifier: Programming Language :: Python :: 3.9
Classifier: Programming Language :: Python :: 3.10
Classifier: Programming Language :: Python :: 3.11
Classifier: License :: OSI Approved :: MIT License
Classifier: Operating System :: Microsoft :: Windows
Classifier: Topic :: Office/Business :: Financial :: Investment
Classifier: Topic :: Software Development :: Libraries :: Python Modules
Requires-Python: >=3.8
Requires-Dist: grpcio>=1.68.1
Requires-Dist: grpcio-tools>=1.68.1
Requires-Dist: protobuf>=5.29.2
Requires-Dist: pytz>=2024.2
Requires-Dist: MetaTrader5>=5.0.33
Requires-Dist: mt5_grpc_proto>=0.2.1
Provides-Extra: dev
Requires-Dist: pytest>=7.0.0; extra == "dev"
Requires-Dist: pytest-cov>=4.0.0; extra == "dev"
Requires-Dist: black>=23.0.0; extra == "dev"
Requires-Dist: isort>=5.0.0; extra == "dev"
Requires-Dist: mypy>=1.0.0; extra == "dev"
Requires-Dist: build>=1.0.0; extra == "dev"
Requires-Dist: twine>=4.0.0; extra == "dev"
Dynamic: author
Dynamic: author-email
Dynamic: classifier
Dynamic: description
Dynamic: description-content-type
Dynamic: home-page
Dynamic: keywords
Dynamic: project-url
Dynamic: provides-extra
Dynamic: requires-dist
Dynamic: requires-python
Dynamic: summary
